{
  "num_iid": "625757809636",
  "title": "简易鞋架子家用现代放门口收纳神器网红防尘小鞋柜宿舍室内好看",
  "desc_short": "",
  "price": "13.9",
  "total_price": "",
  "suggestive_price": "",
  "orginal_price": "27.80",
  "nick": "守候家居旗舰店",
  "num": "200",
  "detail_url": "https://item.taobao.com/item.htm?id=625757809636",
  "pic_url": "//img.alicdn.com/imgextra/i1/1962117854/O1CN01S5oStG27tBLPpXfK6_!!0-item_pic.jpg",
  "brand": "守候",
  "brandId": "8073460",
  "rootCatId": "50008164",
  "cid": "50006533",
  "desc": "",
  "item_imgs": [
    {
      "url": "//img.alicdn.com/imgextra/i1/1962117854/O1CN01S5oStG27tBLPpXfK6_!!0-item_pic.jpg"
    },
    {
      "url": "//img.alicdn.com/imgextra/i2/1962117854/O1CN01wzLALj27tBL8Pq7FO_!!1962117854.jpg"
    },
    {
      "url": "//img.alicdn.com/imgextra/i4/1962117854/O1CN01bmpGwV27tBL6I2BvQ_!!0-item_pic.jpg"
    },
    {
      "url": "//img.alicdn.com/imgextra/i4/1962117854/O1CN0180TuR827tBJtY4lnm_!!1962117854.jpg"
    },
    {
      "url": "//img.alicdn.com/imgextra/i1/1962117854/O1CN01tuIE7z27tBJp2btO6_!!1962117854.jpg"
    }
  ],
  "item_weight": "",
  "post_fee": 0,
  "freight": "快递: 免运费",
  "express_fee": null,
  "ems_fee": "",
  "shipping_to": "镜湖区",
  "video": [],
  "sample_id": "",
  "props_name": "1627207:28332:颜色分类:SK款3层黑色（长61.5cm）;1627207:30156:颜色分类:SK款4层黑色（长61.5cm）;1627207:60092:颜色分类:SK款4层黑色（长61.5cm）--升级防水垫片;1627207:3232483:颜色分类:SK款大4层黑色（长91.5cm）--每层可放5双鞋;1627207:3232482:颜色分类:SK款5层黑色（长61.5cm）;1627207:3232478:颜色分类:SK款5层黑色（长61.5cm）--升级防水垫片;1627207:3232484:颜色分类:SK款大5层黑色（长91.5cm）--每层可放5双成人鞋;1627207:3232479:颜色分类:SK款6层黑色（长61.5cm）;1627207:28340:颜色分类:SK款6层黑色（长61.5cm）--升级防水垫片;1627207:3232481:颜色分类:SK款大6层黑色（长91.5cm）--每层可放5双成人鞋;1627207:28320:颜色分类:SK款7层黑色（长61.5cm）;1627207:3232480:颜色分类:SK款7层黑色（长61.5cm）--升级防水垫片;1627207:90554:颜色分类:SK款大7层黑色（长91.5cm）--每层可放5双成人鞋;1627207:80882:颜色分类:SK款8层黑色（长61.5cm）;1627207:28329:颜色分类:SK款8层黑色（长61.5cm）--升级防水垫片",
  "prop_imgs": {
    "prop_img": [
      {
        "properties": "1627207:28332",
        "url": "//img.alicdn.com/imgextra/i3/1962117854/O1CN01gb7O2B27tBKNUXwIp_!!1962117854.jpg"
      },
      {
        "properties": "1627207:30156",
        "url": "//img.alicdn.com/imgextra/i2/1962117854/O1CN01MYn6MN27tBKNUXjrD_!!1962117854.jpg"
      },
      {
        "properties": "1627207:60092",
        "url": "//img.alicdn.com/imgextra/i2/1962117854/O1CN016yPXaG27tBKNDez0j_!!1962117854.jpg"
      },
      {
        "properties": "1627207:3232483",
        "url": "//img.alicdn.com/imgextra/i1/1962117854/O1CN01H6LUnw27tBKQ2t1OE_!!1962117854.jpg"
      },
      {
        "properties": "1627207:3232482",
        "url": "//img.alicdn.com/imgextra/i2/1962117854/O1CN017JEsND27tBKNagKcl_!!1962117854.jpg"
      },
      {
        "properties": "1627207:3232478",
        "url": "//img.alicdn.com/imgextra/i2/1962117854/O1CN01jOzCnb27tBKT43ktI_!!1962117854.jpg"
      },
      {
        "properties": "1627207:3232484",
        "url": "//img.alicdn.com/imgextra/i1/1962117854/O1CN01yXbQzK27tBKPNmw0D_!!1962117854.jpg"
      },
      {
        "properties": "1627207:3232479",
        "url": "//img.alicdn.com/imgextra/i2/1962117854/O1CN01HT2iLs27tBKQNicu8_!!1962117854.jpg"
      },
      {
        "properties": "1627207:28340",
        "url": "//img.alicdn.com/imgextra/i3/1962117854/O1CN01stFaI627tBL9g5nIZ_!!1962117854.jpg"
      },
      {
        "properties": "1627207:3232481",
        "url": "//img.alicdn.com/imgextra/i3/1962117854/O1CN01Fdvxap27tBKNakI2w_!!1962117854.jpg"
      },
      {
        "properties": "1627207:28320",
        "url": "//img.alicdn.com/imgextra/i1/1962117854/O1CN01oBCYYr27tBKOI2s1j_!!1962117854.jpg"
      },
      {
        "properties": "1627207:3232480",
        "url": "//img.alicdn.com/imgextra/i2/1962117854/O1CN01fUpebL27tBKREXmJn_!!1962117854.jpg"
      },
      {
        "properties": "1627207:90554",
        "url": "//img.alicdn.com/imgextra/i2/1962117854/O1CN01nf0uxH27tBKRs3aCk_!!1962117854.jpg"
      },
      {
        "properties": "1627207:80882",
        "url": "//img.alicdn.com/imgextra/i2/1962117854/O1CN01AAtRTz27tBKNDmVC9_!!1962117854.jpg"
      },
      {
        "properties": "1627207:28329",
        "url": "//img.alicdn.com/imgextra/i4/1962117854/O1CN01PjgPni27tBKNaoWIL_!!1962117854.jpg"
      }
    ]
  },
  "props_imgs": {
    "prop_img": [
      {
        "properties": "1627207:28332",
        "url": "//img.alicdn.com/imgextra/i3/1962117854/O1CN01gb7O2B27tBKNUXwIp_!!1962117854.jpg"
      },
      {
        "properties": "1627207:30156",
        "url": "//img.alicdn.com/imgextra/i2/1962117854/O1CN01MYn6MN27tBKNUXjrD_!!1962117854.jpg"
      },
      {
        "properties": "1627207:60092",
        "url": "//img.alicdn.com/imgextra/i2/1962117854/O1CN016yPXaG27tBKNDez0j_!!1962117854.jpg"
      },
      {
        "properties": "1627207:3232483",
        "url": "//img.alicdn.com/imgextra/i1/1962117854/O1CN01H6LUnw27tBKQ2t1OE_!!1962117854.jpg"
      },
      {
        "properties": "1627207:3232482",
        "url": "//img.alicdn.com/imgextra/i2/1962117854/O1CN017JEsND27tBKNagKcl_!!1962117854.jpg"
      },
      {
        "properties": "1627207:3232478",
        "url": "//img.alicdn.com/imgextra/i2/1962117854/O1CN01jOzCnb27tBKT43ktI_!!1962117854.jpg"
      },
      {
        "properties": "1627207:3232484",
        "url": "//img.alicdn.com/imgextra/i1/1962117854/O1CN01yXbQzK27tBKPNmw0D_!!1962117854.jpg"
      },
      {
        "properties": "1627207:3232479",
        "url": "//img.alicdn.com/imgextra/i2/1962117854/O1CN01HT2iLs27tBKQNicu8_!!1962117854.jpg"
      },
      {
        "properties": "1627207:28340",
        "url": "//img.alicdn.com/imgextra/i3/1962117854/O1CN01stFaI627tBL9g5nIZ_!!1962117854.jpg"
      },
      {
        "properties": "1627207:3232481",
        "url": "//img.alicdn.com/imgextra/i3/1962117854/O1CN01Fdvxap27tBKNakI2w_!!1962117854.jpg"
      },
      {
        "properties": "1627207:28320",
        "url": "//img.alicdn.com/imgextra/i1/1962117854/O1CN01oBCYYr27tBKOI2s1j_!!1962117854.jpg"
      },
      {
        "properties": "1627207:3232480",
        "url": "//img.alicdn.com/imgextra/i2/1962117854/O1CN01fUpebL27tBKREXmJn_!!1962117854.jpg"
      },
      {
        "properties": "1627207:90554",
        "url": "//img.alicdn.com/imgextra/i2/1962117854/O1CN01nf0uxH27tBKRs3aCk_!!1962117854.jpg"
      },
      {
        "properties": "1627207:80882",
        "url": "//img.alicdn.com/imgextra/i2/1962117854/O1CN01AAtRTz27tBKNDmVC9_!!1962117854.jpg"
      },
      {
        "properties": "1627207:28329",
        "url": "//img.alicdn.com/imgextra/i4/1962117854/O1CN01PjgPni27tBKNaoWIL_!!1962117854.jpg"
      }
    ]
  },
  "property_alias": "",
  "props": [
    {
      "name": "品牌",
      "value": "守候"
    },
    {
      "name": "型号",
      "value": "SH7855"
    },
    {
      "name": "风格",
      "value": "简约现代"
    },
    {
      "name": "颜色分类",
      "value": "SK款7层黑色（长61.5cm） SK款8层黑色（长61.5cm）--升级防水垫片 SK款3层黑色（长61.5cm） SK款6层黑色（长61.5cm）--升级防水垫片 SK款4层黑色（长61.5cm） SK款4层黑色（长61.5cm）--升级防水垫片 SK款8层黑色（长61.5cm） SK款大7层黑色（长91.5cm）--每层可放5双成人鞋 SK款5层黑色（长61.5cm）--升级防水垫片 SK款6层黑色（长61.5cm） SK款7层黑色（长61.5cm）--升级防水垫片 SK款大6层黑色（长91.5cm）--每层可放5双成人鞋 SK款5层黑色（长61.5cm） SK款大4层黑色（长91.5cm）--每层可放5双鞋 SK款大5层黑色（长91.5cm）--每层可放5双成人鞋"
    },
    {
      "name": "是否可定制",
      "value": "否"
    },
    {
      "name": "附加功能",
      "value": "可移动"
    },
    {
      "name": "家具结构",
      "value": "支架结构"
    },
    {
      "name": "产地",
      "value": "湖北省"
    },
    {
      "name": "地市",
      "value": "武汉市"
    },
    {
      "name": "区县",
      "value": "东西湖区"
    },
    {
      "name": "包装体积",
      "value": "0.1"
    },
    {
      "name": "出租车是否可运输",
      "value": "是"
    },
    {
      "name": "款式定位",
      "value": "经济型"
    }
  ],
  "total_sold": "7426",
  "skus": {
    "sku": [
      {
        "price": "13.9",
        "total_price": 0,
        "orginal_price": "13.9",
        "properties": "1627207:28332",
        "properties_name": "1627207:28332:颜色分类:SK款3层黑色（长61.5cm）",
        "quantity": "200",
        "sku_id": "4642695055795"
      },
      {
        "price": "17.9",
        "total_price": 0,
        "orginal_price": "17.9",
        "properties": "1627207:30156",
        "properties_name": "1627207:30156:颜色分类:SK款4层黑色（长61.5cm）",
        "quantity": "200",
        "sku_id": "4642695055796"
      },
      {
        "price": "21.9",
        "total_price": 0,
        "orginal_price": "21.9",
        "properties": "1627207:60092",
        "properties_name": "1627207:60092:颜色分类:SK款4层黑色（长61.5cm）--升级防水垫片",
        "quantity": "200",
        "sku_id": "4642695055800"
      },
      {
        "price": "22.9",
        "total_price": 0,
        "orginal_price": "22.9",
        "properties": "1627207:3232483",
        "properties_name": "1627207:3232483:颜色分类:SK款大4层黑色（长91.5cm）--每层可放5双鞋",
        "quantity": "200",
        "sku_id": "4609194679128"
      },
      {
        "price": "21.9",
        "total_price": 0,
        "orginal_price": "21.9",
        "properties": "1627207:3232482",
        "properties_name": "1627207:3232482:颜色分类:SK款5层黑色（长61.5cm）",
        "quantity": "200",
        "sku_id": "4642695055799"
      },
      {
        "price": "25.9",
        "total_price": 0,
        "orginal_price": "25.9",
        "properties": "1627207:3232478",
        "properties_name": "1627207:3232478:颜色分类:SK款5层黑色（长61.5cm）--升级防水垫片",
        "quantity": "200",
        "sku_id": "4642695055797"
      },
      {
        "price": "26.9",
        "total_price": 0,
        "orginal_price": "26.9",
        "properties": "1627207:3232484",
        "properties_name": "1627207:3232484:颜色分类:SK款大5层黑色（长91.5cm）--每层可放5双成人鞋",
        "quantity": "200",
        "sku_id": "4609194679129"
      },
      {
        "price": "25.9",
        "total_price": 0,
        "orginal_price": "25.9",
        "properties": "1627207:3232479",
        "properties_name": "1627207:3232479:颜色分类:SK款6层黑色（长61.5cm）",
        "quantity": "200",
        "sku_id": "4642969819627"
      },
      {
        "price": "29.9",
        "total_price": 0,
        "orginal_price": "29.9",
        "properties": "1627207:28340",
        "properties_name": "1627207:28340:颜色分类:SK款6层黑色（长61.5cm）--升级防水垫片",
        "quantity": "200",
        "sku_id": "4642969819626"
      },
      {
        "price": "30.9",
        "total_price": 0,
        "orginal_price": "30.9",
        "properties": "1627207:3232481",
        "properties_name": "1627207:3232481:颜色分类:SK款大6层黑色（长91.5cm）--每层可放5双成人鞋",
        "quantity": "200",
        "sku_id": "4642695055798"
      },
      {
        "price": "29.9",
        "total_price": 0,
        "orginal_price": "29.9",
        "properties": "1627207:28320",
        "properties_name": "1627207:28320:颜色分类:SK款7层黑色（长61.5cm）",
        "quantity": "200",
        "sku_id": "4642969819624"
      },
      {
        "price": "33.9",
        "total_price": 0,
        "orginal_price": "33.9",
        "properties": "1627207:3232480",
        "properties_name": "1627207:3232480:颜色分类:SK款7层黑色（长61.5cm）--升级防水垫片",
        "quantity": "200",
        "sku_id": "4642969819628"
      },
      {
        "price": "34.9",
        "total_price": 0,
        "orginal_price": "34.9",
        "properties": "1627207:90554",
        "properties_name": "1627207:90554:颜色分类:SK款大7层黑色（长91.5cm）--每层可放5双成人鞋",
        "quantity": "200",
        "sku_id": "4642695055801"
      },
      {
        "price": "33.9",
        "total_price": 0,
        "orginal_price": "33.9",
        "properties": "1627207:80882",
        "properties_name": "1627207:80882:颜色分类:SK款8层黑色（长61.5cm）",
        "quantity": "200",
        "sku_id": "4642969819629"
      },
      {
        "price": "37.9",
        "total_price": 0,
        "orginal_price": "37.9",
        "properties": "1627207:28329",
        "properties_name": "1627207:28329:颜色分类:SK款8层黑色（长61.5cm）--升级防水垫片",
        "quantity": "200",
        "sku_id": "4642969819625"
      }
    ]
  },
  "seller_id": "1962117854",
  "sales": 4000,
  "shop_id": "108404939",
  "props_list": {
    "1627207:28332": "颜色分类:SK款3层黑色（长61.5cm）",
    "1627207:30156": "颜色分类:SK款4层黑色（长61.5cm）",
    "1627207:60092": "颜色分类:SK款4层黑色（长61.5cm）--升级防水垫片",
    "1627207:3232483": "颜色分类:SK款大4层黑色（长91.5cm）--每层可放5双鞋",
    "1627207:3232482": "颜色分类:SK款5层黑色（长61.5cm）",
    "1627207:3232478": "颜色分类:SK款5层黑色（长61.5cm）--升级防水垫片",
    "1627207:3232484": "颜色分类:SK款大5层黑色（长91.5cm）--每层可放5双成人鞋",
    "1627207:3232479": "颜色分类:SK款6层黑色（长61.5cm）",
    "1627207:28340": "颜色分类:SK款6层黑色（长61.5cm）--升级防水垫片",
    "1627207:3232481": "颜色分类:SK款大6层黑色（长91.5cm）--每层可放5双成人鞋",
    "1627207:28320": "颜色分类:SK款7层黑色（长61.5cm）",
    "1627207:3232480": "颜色分类:SK款7层黑色（长61.5cm）--升级防水垫片",
    "1627207:90554": "颜色分类:SK款大7层黑色（长91.5cm）--每层可放5双成人鞋",
    "1627207:80882": "颜色分类:SK款8层黑色（长61.5cm）",
    "1627207:28329": "颜色分类:SK款8层黑色（长61.5cm）--升级防水垫片"
  },
  "seller_info": {
    "nick": "守候家居旗舰店",
    "item_score": "4.7 ",
    "score_p": "4.7 ",
    "delivery_score": "4.7 ",
    "shop_type": "B",
    "user_num_id": "1962117854",
    "sid": "108404939",
    "title": "守候家居旗舰店",
    "zhuy": "https://shop108404939.taobao.com/",
    "shop_name": "守候家居旗舰店"
  },
  "tmall": true,
  "error": "",
  "fav_count": "15688",
  "fans_count": "1.7万",
  "location": "湖北武汉",
  "data_from": "jcs",
  "has_discount": "true",
  "is_promotion": "true",
  "promo_type": null,
  "props_img": {
    "1627207:28332": "//img.alicdn.com/imgextra/i3/1962117854/O1CN01gb7O2B27tBKNUXwIp_!!1962117854.jpg",
    "1627207:30156": "//img.alicdn.com/imgextra/i2/1962117854/O1CN01MYn6MN27tBKNUXjrD_!!1962117854.jpg",
    "1627207:60092": "//img.alicdn.com/imgextra/i2/1962117854/O1CN016yPXaG27tBKNDez0j_!!1962117854.jpg",
    "1627207:3232483": "//img.alicdn.com/imgextra/i1/1962117854/O1CN01H6LUnw27tBKQ2t1OE_!!1962117854.jpg",
    "1627207:3232482": "//img.alicdn.com/imgextra/i2/1962117854/O1CN017JEsND27tBKNagKcl_!!1962117854.jpg",
    "1627207:3232478": "//img.alicdn.com/imgextra/i2/1962117854/O1CN01jOzCnb27tBKT43ktI_!!1962117854.jpg",
    "1627207:3232484": "//img.alicdn.com/imgextra/i1/1962117854/O1CN01yXbQzK27tBKPNmw0D_!!1962117854.jpg",
    "1627207:3232479": "//img.alicdn.com/imgextra/i2/1962117854/O1CN01HT2iLs27tBKQNicu8_!!1962117854.jpg",
    "1627207:28340": "//img.alicdn.com/imgextra/i3/1962117854/O1CN01stFaI627tBL9g5nIZ_!!1962117854.jpg",
    "1627207:3232481": "//img.alicdn.com/imgextra/i3/1962117854/O1CN01Fdvxap27tBKNakI2w_!!1962117854.jpg",
    "1627207:28320": "//img.alicdn.com/imgextra/i1/1962117854/O1CN01oBCYYr27tBKOI2s1j_!!1962117854.jpg",
    "1627207:3232480": "//img.alicdn.com/imgextra/i2/1962117854/O1CN01fUpebL27tBKREXmJn_!!1962117854.jpg",
    "1627207:90554": "//img.alicdn.com/imgextra/i2/1962117854/O1CN01nf0uxH27tBKRs3aCk_!!1962117854.jpg",
    "1627207:80882": "//img.alicdn.com/imgextra/i2/1962117854/O1CN01AAtRTz27tBKNDmVC9_!!1962117854.jpg",
    "1627207:28329": "//img.alicdn.com/imgextra/i4/1962117854/O1CN01PjgPni27tBKNaoWIL_!!1962117854.jpg"
  },
  "desc_img": [],
  "shop_item": [],
  "relate_items": []
}
